{
  "id_nortag": "-967470465",
  "index_page": 0,
  "name_nortag": "Mei Terumi",
  "total_img": 3,
  "total_page": 0,
  "hc_lt_alb": "-1200134418",
  "hc_lt_data_img": "244036902",
  "hc_lt_nortag": "-1005947798",
  "hc_lt_sptag": "",
  "lt_alb": [
    {
      "id_alb": "66988",
      "name_alb": "Boy",
      "total_img": 8592
    },
    {
      "id_alb": "-1968799663",
      "name_alb": "Naruto",
      "total_img": 478
    }
  ],
  "lt_data_img": [
    {
      "hc_lt_id_alb": "-831277070",
      "hc_lt_id_nortag": "-1808652642",
      "hc_lt_id_sptag": "",
      "id_img": "Naruto_665369_crop2608_-165825055",
      "link_img": "UTb0sGqADnbLiHq9qhRMRkSRiLND0Tk7ctN8tpraiifGuCLdvpTuVhRT7wmJT6SpaQuZzpwIVyBaRYSG8sSoW5Vy4706IhQgSYlgwrgVRHU=",
      "thumb": "UTb0sGqADnbLiHq9qhRMRkSRiLND0Tk7ctN8tpraiifGuCLdvpTuVhRT7wmJT6Spi/js8wpWWnOJP9LTzG4+4ZVy4706IhQgSYlgwrgVRHU=",
      "lt_id_alb": [
        "-1968799663"
      ],
      "list_id_nortag": [
        "1575701767",
        "-967470465",
        "-1493578597",
        "-2019930864"
      ]
    },
    {
      "hc_lt_id_alb": "-831277070",
      "hc_lt_id_nortag": "-1919143840",
      "hc_lt_id_sptag": "",
      "id_img": "Naruto_644183_crop2608_16543516",
      "link_img": "UTb0sGqADnbLiHq9qhRMRkSRiLND0Tk7ctN8tpraiidi0R+RY+9mC06wntWlX2JEfICMyV4zT5ei6k+ZhRda25Vy4706IhQgSYlgwrgVRHU=",
      "thumb": "UTb0sGqADnbLiHq9qhRMRkSRiLND0Tk7ctN8tpraiidi0R+RY+9mC06wntWlX2JEljAK5xwOcNiYz7mAYLvowJVy4706IhQgSYlgwrgVRHU=",
      "lt_id_alb": [
        "-1968799663"
      ],
      "list_id_nortag": [
        "1575701767",
        "-148568472",
        "-967470465",
        "-1493578597",
        "-2019930864"
      ]
    },
    {
      "hc_lt_id_alb": "766321787",
      "hc_lt_id_nortag": "-224285459",
      "hc_lt_id_sptag": "",
      "id_img": "Naruto_106960_crop2608_499946844",
      "link_img": "UTb0sGqADnbLiHq9qhRMRkSRiLND0Tk7ctN8tpraiidUQ7KZ1hAS+ubRerPhxOqD2Xs8pj7k551+g6nWrESL+5Vy4706IhQgSYlgwrgVRHU=",
      "thumb": "UTb0sGqADnbLiHq9qhRMRkSRiLND0Tk7ctN8tpraiidUQ7KZ1hAS+ubRerPhxOqDdkLqsfkRXX5qX4KB/L9xsZVy4706IhQgSYlgwrgVRHU=",
      "lt_id_alb": [
        "66988",
        "-1968799663"
      ],
      "list_id_nortag": [
        "-967470465",
        "-1493578597",
        "-2019930864",
        "154658675"
      ]
    }
  ],
  "lt_nortag": [
    {
      "id_nortag": "-2019930864",
      "name_nortag": "A Naruto",
      "total_img": 3
    },
    {
      "id_nortag": "-1493578597",
      "name_nortag": "Gaara Naruto",
      "total_img": 40
    },
    {
      "id_nortag": "-148568472",
      "name_nortag": "Madara Uchiha",
      "total_img": 21
    },
    {
      "id_nortag": "-967470465",
      "name_nortag": "Mei Terumi",
      "total_img": 3
    },
    {
      "id_nortag": "154658675",
      "name_nortag": "Naruto Uzumaki",
      "total_img": 292
    },
    {
      "id_nortag": "1575701767",
      "name_nortag": "Tsunade Naruto",
      "total_img": 6
    }
  ]
}